{
  "/_app": "pages/_app.js",
  "/api/hello": "pages/api/hello.js",
  "/api/submit-form": "pages/api/submit-form.js",
  "/api/subscribe": "pages/api/subscribe.js",
  "/blog-details": "pages/blog-details.js",
  "/blog-standard": "pages/blog-standard.js",
  "/book-your-wedding": "pages/book-your-wedding.js",
  "/checkout": "pages/checkout.js",
  "/cart": "pages/cart.js",
  "/contact": "pages/contact.js",
  "/faqs": "pages/faqs.js",
  "/index-2": "pages/index-2.js",
  "/index-4": "pages/index-4.js",
  "/farmers": "pages/farmers.js",
  "/portfolio-details": "pages/portfolio-details.js",
  "/portfolio-full-width": "pages/portfolio-full-width.js",
  "/products-left-sidebar": "pages/products-left-sidebar.js",
  "/product-details": "pages/product-details.js",
  "/products-right-sidebar": "pages/products-right-sidebar.js",
  "/service-details": "pages/service-details.js",
  "/about": "pages/about.js",
  "/the-property": "pages/the-property.js",
  "/products": "pages/products.js",
  "/_error": "pages/_error.js",
  "/services": "pages/services.js",
  "/blog": "pages/blog.js",
  "/": "pages/index.js",
  "/blog/[blogid]": "pages/blog/[blogid].js",
  "/index-5": "pages/index-5.js",
  "/_document": "pages/_document.js"
}